{"else":{"name":"something","chats":[["sent","something"],["sent","somethsing"],["sent","cxvxc"],["sent","even more bug fixing done"]]},"somethingthatdoesn'tworkyet":{"name":"a new contact","chats":[["sent","big black men"],["sent","I can send"],["sent","messages"],["sent","cool"],["sent","I also worked on recieving messages"],["sent","i just have to make someone send messages to me when the server is ready"],["sent","it even saves the chat"]]},"work":{"name":"sad","chats":[["sent","done?"],["sent","nice"]]}}